setup.py
aiocore/__init__.py
aiocore/aiocore.py
aiocore.egg-info/PKG-INFO
aiocore.egg-info/SOURCES.txt
aiocore.egg-info/dependency_links.txt
aiocore.egg-info/top_level.txt