Metadata-Version: 1.0
Name: aiocore
Version: 0.1
Summary: does some stuff with things & stuff
Home-page: UNKNOWN
Author: Paul Tagliamonte
Author-email: paultag@debian.org
License: Expat
Platform: any
